monoliths/__init__.py
monoliths/monoliths.py
monoliths-0.2.0.dist-info/LICENSE
monoliths-0.2.0.dist-info/METADATA
monoliths-0.2.0.dist-info/WHEEL
monoliths-0.2.0.dist-info/top_level.txt
monoliths-0.2.0.dist-info/RECORD
