Metadata-Version: 2.1
Name: monoliths
Version: 0.2.0
Summary: Python tool for automatically wrapping a multi-module Python library into a single portable module file.
Home-page: https://github.com/reity/monoliths
Author: Andrei Lapets
Author-email: a@lapets.io
License: MIT
Platform: UNKNOWN
